aikits/__init__.py
aikits/aikits.py
aikits-0.1.0.dist-info/METADATA
aikits-0.1.0.dist-info/WHEEL
aikits-0.1.0.dist-info/entry_points.txt
aikits-0.1.0.dist-info/licenses/LICENSE
aikits-0.1.0.dist-info/RECORD
