Metadata-Version: 2.4
Name: aikits
Version: 0.1.0
Summary: A package to download ai tools templates and agents
Project-URL: Repository, https://github.com/alexboone29/aikits
Author-email: neutralbase <alex@neutralbase.com>
License-Expression: MIT
License-File: LICENSE
Requires-Python: <4.0,>=3.11
